cli.py
metext/__init__.py
metext/__version__.py
metext/plugin_base.py
metext/plugins/__init__.py
metext/plugins/decoders/__init__.py
metext/plugins/decoders/base16.py
metext/plugins/decoders/base32.py
metext/plugins/decoders/base58.py
metext/plugins/decoders/base64.py
metext/plugins/decoders/base85.py
metext/plugins/decoders/base91.py
metext/plugins/decoders/bech32.py
metext/plugins/decoders/binhex.py
metext/plugins/decoders/cert.py
metext/plugins/decoders/gzip.py
metext/plugins/decoders/id.py
metext/plugins/decoders/mime.py
metext/plugins/decoders/percent.py
metext/plugins/decoders/quopri.py
metext/plugins/decoders/segwit.py
metext/plugins/decoders/uu.py
metext/plugins/decoders/yenc.py
metext/plugins/extractors/__init__.py
metext/plugins/extractors/baseenc.py
metext/plugins/extractors/crypto.py
metext/plugins/extractors/doi.py
metext/plugins/extractors/email.py
metext/plugins/extractors/guid.py
metext/plugins/extractors/hash.py
metext/plugins/extractors/ip.py
metext/plugins/extractors/isbn.py
metext/plugins/extractors/issn.py
metext/plugins/extractors/json.py
metext/plugins/extractors/mac.py
metext/plugins/extractors/pem.py
metext/plugins/extractors/uri.py
metext/plugins/printers/__init__.py
metext/plugins/printers/csv.py
metext/plugins/printers/json.py
metext/plugins/printers/table.py
metext/plugins/validators/__init__.py
metext/plugins/validators/baseenc.py
metext/plugins/validators/crypto.py
metext/plugins/validators/doi.py
metext/plugins/validators/email.py
metext/plugins/validators/hash.py
metext/plugins/validators/ip.py
metext/plugins/validators/isbn.py
metext/plugins/validators/issn.py
metext/plugins/validators/uri.py
metext/utils/__init__.py
metext/utils/fileinput.py
metext/utils/regex.py
metext/utils/sabyenc.py
metext/utils/ss58.py
metext/utils/uri.py
metext/utils/z85.py
metext/utils/_torf/__init__.py
metext/utils/_torf/_errors.py
metext/utils/_torf/_magnet.py
metext/utils/_torf/_utils.py
metext-0.0.3.dist-info/LICENSE.txt
metext-0.0.3.dist-info/METADATA
metext-0.0.3.dist-info/WHEEL
metext-0.0.3.dist-info/entry_points.txt
metext-0.0.3.dist-info/top_level.txt
metext-0.0.3.dist-info/RECORD
