Metadata-Version: 2.1
Name: metext
Version: 0.0.3
Summary: A tool to search for data patterns in (encoded) binary data
Home-page: https://github.com/espoem/MetExt
Author: Martin Šmíd
License: LGPLv3+
Project-URL: Source, https://github.com/espoem/MetExt
Project-URL: Tracker, https://github.com/espoem/MetExt/issues
Platform: UNKNOWN
Classifier: Development Status :: 3 - Alpha
Classifier: Intended Audience :: Developers
Classifier: License :: OSI Approved :: GNU Lesser General Public License v3 or later (LGPLv3+)
Classifier: Programming Language :: Python :: 3
Requires-Python: >=3.5
Requires-Dist: pytest
Requires-Dist: email-validator
Requires-Dist: tabulate
Requires-Dist: base91
Requires-Dist: pysha3
Requires-Dist: base32-crockford
Requires-Dist: chardet
Requires-Dist: pem
Requires-Dist: cashaddress
Requires-Dist: cbor
Requires-Dist: base58
Requires-Dist: regex
Requires-Dist: requests
Requires-Dist: netaddr
Requires-Dist: brotli
Requires-Dist: filetype
Requires-Dist: btclib (==2020.12.19) ; python_version > "3.5"
